mystrom2mqtt/__init__.py
mystrom2mqtt-0.1.0.dist-info/LICENSE.md
mystrom2mqtt-0.1.0.dist-info/METADATA
mystrom2mqtt-0.1.0.dist-info/WHEEL
mystrom2mqtt-0.1.0.dist-info/entry_points.txt
mystrom2mqtt-0.1.0.dist-info/top_level.txt
mystrom2mqtt-0.1.0.dist-info/zip-safe
mystrom2mqtt-0.1.0.dist-info/RECORD
