Metadata-Version: 2.1
Name: mystrom2mqtt
Version: 0.1.0
Summary: Transfer HTTP requests from myStrom devices to MQTT
Home-page: https://github.com/home-assistant-ecosystem/mystrom2mqtt
Author: Fabian Affolter
Author-email: fabian@affolter-engineering.ch
License: ASL 2.0
Keywords: iot mystrom mqtt homeassistant
Platform: UNKNOWN
Classifier: Development Status :: 3 - Alpha
Classifier: Environment :: Console
Classifier: Intended Audience :: Developers
Classifier: License :: OSI Approved :: Apache Software License
Classifier: Operating System :: MacOS :: MacOS X
Classifier: Operating System :: Microsoft :: Windows
Classifier: Operating System :: POSIX
Classifier: Programming Language :: Python :: 3.8
Classifier: Programming Language :: Python :: 3.9
Classifier: Topic :: Utilities
Requires-Dist: fastapi
Requires-Dist: uvicorn
Requires-Dist: toml
Requires-Dist: netaddr
Requires-Dist: asyncio-mqtt
